{
    "variables":[ 
        {
            "REG_CASO_NO": "String",
            "REG_ANIO": "String",
            "MES_REG": "String",
            "REG_DIA": "String",
            "REG_MUNI": "String",
            "QUIEN_REPORTA": "String",
            "VIC_NOM": "String",
            "VIC_SEXO": "String",
            "VIC_EDAD": "String",
            "VIC_ANIO_NAC": "String",
            "VIC_MES_NAC": "String",
            "VIC_DIA_NAC": "String",
            "VIC_HIJ_TOT": "String",
            "VIC_HIJ_SEX": "String",
            "VIC_HIJ_EDAD": "String",
            "VIC_ALFAB": "String",
            "VIC_ESCOLARIDAD": "String",
            "VIC_EST_CONY": "String",
            "VIC_MUNI_RES": "String",
            "VIC_PUEB_PER": "String",
            "VIC_NACIONAL": "String",
            "VIC_TRABAJA": "String",
            "VIC_OCUP": "String",
            "VIC_DEDICA": "String",
            "VIC_DISC": "String",
            "VIC_TIPO_DISC": "String",
            "VIC_REL_AGR": "String",
            "ESP_OTR_REL": "String",
            "OTRAS_VICTIMAS": "String",
            "OTRAS_VIC_SEX": "String",
            "OTRAS_VIC_EDAD": "String",
            "OTRAS_VIC_REL": "String",
            "HEC_DIA": "String",
            "HEC_MES": "String",
            "HEC_ANO": "String",
            "HEC_DEPTOMCPIO": "String",
            "HEC_AREA": "String",
            "HEC_TIPAGRE": "String",
            "HEC_RECUR_CASO": "String",
            "INST_RECUR_CASO": "String",
            "AGR_SEXO": "String",
            "AGR_EDAD": "String",
            "AGR_ALFAB": "String",
            "AGR_ESCOLARIDAD": "String",
            "AGR_EST_CONY": "String",
            "AGR_PUEB_PER": "String",
            "AGR_NACIONAL": "String",
            "AGR_TRABAJA": "String",
            "AGR_OCUP": "String",
            "AGR_DEDICA": "String",
            "OTROS_AGR_TOT": "String",
            "OTROS_AGR_SEX": "String",
            "OTROS_AGR_EDAD": "String",
            "OTROS_AGR_REL": "String",
            "DIL_GES": "String",
            "REM_CASO": "String",
            "REG_INST_HECH": "String"
        },
        {
            "REG_CASO_NO": "Alos",
            "REG_ANIO": "Alos",
            "MES_REG": "Alos",
            "REG_DIA": "Alos",
            "REG_MUNI": "Alos",
            "QUIEN_REPORTA": "Alos",
            "VIC_NOM": "Alos",
            "VIC_SEXO": "Alos",
            "VIC_EDAD": "Alos",
            "VIC_ANIO_NAC": "Alos",
            "VIC_MES_NAC": "Alos",
            "VIC_DIA_NAC": "Alos",
            "VIC_HIJ_TOT": "Alos",
            "VIC_HIJ_SEX": "Alos",
            "VIC_HIJ_EDAD": "Alos",
            "VIC_ALFAB": "Alos",
            "VIC_ESCOLARIDAD": "Alos",
            "VIC_EST_CONY": "Alos",
            "VIC_MUNI_RES": "Alos",
            "VIC_PUEB_PER": "Alos",
            "VIC_NACIONAL": "Alos",
            "VIC_TRABAJA": "Alos",
            "VIC_OCUP": "Alos",
            "VIC_DEDICA": "Alos",
            "VIC_DISC": "Alos",
            "VIC_TIPO_DISC": "Alos",
            "VIC_REL_AGR": "Alos",
            "ESP_OTR_REL": "Alos",
            "OTRAS_VICTIMAS": "Alos",
            "OTRAS_VIC_SEX": "Alos",
            "OTRAS_VIC_EDAD": "Alos",
            "OTRAS_VIC_REL": "Alos",
            "HEC_DIA": "Alos",
            "HEC_MES": "Alos",
            "HEC_ANO": "Alos",
            "HEC_DEPTOMCPIO": "Alos",
            "HEC_AREA": "Alos",
            "HEC_TIPAGRE": "Alos",
            "HEC_RECUR_CASO": "Alos",
            "INST_RECUR_CASO": "Alos",
            "AGR_SEXO": "Alos",
            "AGR_EDAD": "Alos",
            "AGR_ALFAB": "Alos",
            "AGR_ESCOLARIDAD": "Alos",
            "AGR_EST_CONY": "Alos",
            "AGR_PUEB_PER": "Alos",
            "AGR_NACIONAL": "Alos",
            "AGR_TRABAJA": "Alos",
            "AGR_OCUP": "Alos",
            "AGR_DEDICA": "Alos",
            "OTROS_AGR_TOT": "Alos",
            "OTROS_AGR_SEX": "Alos",
            "OTROS_AGR_EDAD": "Alos",
            "OTROS_AGR_REL": "Alos",
            "DIL_GES": "Alos",
            "REM_CASO": "Alos",
            "REG_INST_HECH": "Alos"
        },
        {
            "REG_CASO_NO": "hola",
            "REG_ANIO": "hola",
            "MES_REG": "hola",
            "REG_DIA": "hola",
            "REG_MUNI": "hola",
            "QUIEN_REPORTA": "hola",
            "VIC_NOM": "hola",
            "VIC_SEXO": "hola",
            "VIC_EDAD": "hola",
            "VIC_ANIO_NAC": "hola",
            "VIC_MES_NAC": "hola",
            "VIC_DIA_NAC": "hola",
            "VIC_HIJ_TOT": "hola",
            "VIC_HIJ_SEX": "hola",
            "VIC_HIJ_EDAD": "hola",
            "VIC_ALFAB": "hola",
            "VIC_ESCOLARIDAD": "hola",
            "VIC_EST_CONY": "hola",
            "VIC_MUNI_RES": "hola",
            "VIC_PUEB_PER": "hola",
            "VIC_NACIONAL": "hola",
            "VIC_TRABAJA": "hola",
            "VIC_OCUP": "hola",
            "VIC_DEDICA": "hola",
            "VIC_DISC": "hola",
            "VIC_TIPO_DISC": "hola",
            "VIC_REL_AGR": "hola",
            "ESP_OTR_REL": "hola",
            "OTRAS_VICTIMAS": "hola",
            "OTRAS_VIC_SEX": "hola",
            "OTRAS_VIC_EDAD": "hola",
            "OTRAS_VIC_REL": "hola",
            "HEC_DIA": "hola",
            "HEC_MES": "hola",
            "HEC_ANO": "hola",
            "HEC_DEPTOMCPIO": "hola",
            "HEC_AREA": "hola",
            "HEC_TIPAGRE": "hola",
            "HEC_RECUR_CASO": "hola",
            "INST_RECUR_CASO": "hola",
            "AGR_SEXO": "hola",
            "AGR_EDAD": "hola",
            "AGR_ALFAB": "hola",
            "AGR_ESCOLARIDAD": "hola",
            "AGR_EST_CONY": "hola",
            "AGR_PUEB_PER": "hola",
            "AGR_NACIONAL": "hola",
            "AGR_TRABAJA": "hola",
            "AGR_OCUP": "hola",
            "AGR_DEDICA": "hola",
            "OTROS_AGR_TOT": "hola",
            "OTROS_AGR_SEX": "vhola",
            "OTROS_AGR_EDAD": "hola",
            "OTROS_AGR_REL": "hola",
            "DIL_GES": "hola",
            "REM_CASO": "hola",
            "REG_INST_HECH": "hola"
        }
    ]
}